<annotation>
	<folder></folder>
	<filename>1034_jpg.rf.f11967dda6fea25849c1d3d610514054.jpg</filename>
	<path>1034_jpg.rf.f11967dda6fea25849c1d3d610514054.jpg</path>
	<source>
		<database>roboflow.com</database>
	</source>
	<size>
		<width>640</width>
		<height>640</height>
		<depth>3</depth>
	</size>
	<segmented>0</segmented>
	<object>
		<name>drone</name>
		<pose>Unspecified</pose>
		<truncated>0</truncated>
		<difficult>0</difficult>
		<occluded>0</occluded>
		<bndbox>
			<xmin>243</xmin>
			<xmax>345</xmax>
			<ymin>184</ymin>
			<ymax>254</ymax>
		</bndbox>
	</object>
	<metadata>
		<tags>
			<tag>cd</tag>
		</tags>
	</metadata>
</annotation>
