<annotation>
	<folder></folder>
	<filename>208_JPEG_jpg.rf.96ea5d32b68e0ada7597ea47f450d62a.jpg</filename>
	<path>208_JPEG_jpg.rf.96ea5d32b68e0ada7597ea47f450d62a.jpg</path>
	<source>
		<database>roboflow.com</database>
	</source>
	<size>
		<width>640</width>
		<height>640</height>
		<depth>3</depth>
	</size>
	<segmented>0</segmented>
	<object>
		<name>drone</name>
		<pose>Unspecified</pose>
		<truncated>0</truncated>
		<difficult>0</difficult>
		<occluded>0</occluded>
		<bndbox>
			<xmin>207</xmin>
			<xmax>285</xmax>
			<ymin>480</ymin>
			<ymax>568</ymax>
		</bndbox>
	</object>
</annotation>
