<annotation>
	<folder></folder>
	<filename>2398_jpg.rf.d2998fdada6d04f4d344917c0a7cb2d0.jpg</filename>
	<path>2398_jpg.rf.d2998fdada6d04f4d344917c0a7cb2d0.jpg</path>
	<source>
		<database>roboflow.com</database>
	</source>
	<size>
		<width>640</width>
		<height>640</height>
		<depth>3</depth>
	</size>
	<segmented>0</segmented>
	<object>
		<name>drone</name>
		<pose>Unspecified</pose>
		<truncated>0</truncated>
		<difficult>0</difficult>
		<occluded>0</occluded>
		<bndbox>
			<xmin>162</xmin>
			<xmax>380</xmax>
			<ymin>161</ymin>
			<ymax>372</ymax>
		</bndbox>
	</object>
</annotation>
