<annotation>
	<folder></folder>
	<filename>338_JPEG_jpg.rf.9431cafcd83358aa5f920587072a7b48.jpg</filename>
	<path>338_JPEG_jpg.rf.9431cafcd83358aa5f920587072a7b48.jpg</path>
	<source>
		<database>roboflow.com</database>
	</source>
	<size>
		<width>640</width>
		<height>640</height>
		<depth>3</depth>
	</size>
	<segmented>0</segmented>
	<object>
		<name>drone</name>
		<pose>Unspecified</pose>
		<truncated>0</truncated>
		<difficult>0</difficult>
		<occluded>0</occluded>
		<bndbox>
			<xmin>141</xmin>
			<xmax>253</xmax>
			<ymin>87</ymin>
			<ymax>191</ymax>
		</bndbox>
	</object>
	<object>
		<name>drone</name>
		<pose>Unspecified</pose>
		<truncated>0</truncated>
		<difficult>0</difficult>
		<occluded>0</occluded>
		<bndbox>
			<xmin>350</xmin>
			<xmax>431</xmax>
			<ymin>68</ymin>
			<ymax>169</ymax>
		</bndbox>
	</object>
	<metadata>
		<tags>
			<tag>drone</tag>
		</tags>
	</metadata>
</annotation>
