<annotation>
	<folder></folder>
	<filename>4508_jpg.rf.b5f21cbc871d320baf1f82441b1e0406.jpg</filename>
	<path>4508_jpg.rf.b5f21cbc871d320baf1f82441b1e0406.jpg</path>
	<source>
		<database>roboflow.com</database>
	</source>
	<size>
		<width>640</width>
		<height>640</height>
		<depth>3</depth>
	</size>
	<segmented>0</segmented>
	<object>
		<name>drone</name>
		<pose>Unspecified</pose>
		<truncated>0</truncated>
		<difficult>0</difficult>
		<occluded>0</occluded>
		<bndbox>
			<xmin>217</xmin>
			<xmax>408</xmax>
			<ymin>103</ymin>
			<ymax>231</ymax>
		</bndbox>
	</object>
</annotation>
