<annotation>
	<folder></folder>
	<filename>tello_401_jpeg.rf.c31f49acae4fd90a525a86a0db0287ee.jpg</filename>
	<path>tello_401_jpeg.rf.c31f49acae4fd90a525a86a0db0287ee.jpg</path>
	<source>
		<database>roboflow.com</database>
	</source>
	<size>
		<width>640</width>
		<height>640</height>
		<depth>3</depth>
	</size>
	<segmented>0</segmented>
	<object>
		<name>drone</name>
		<pose>Unspecified</pose>
		<truncated>0</truncated>
		<difficult>0</difficult>
		<occluded>0</occluded>
		<bndbox>
			<xmin>178</xmin>
			<xmax>244</xmax>
			<ymin>110</ymin>
			<ymax>184</ymax>
		</bndbox>
	</object>
</annotation>
