<annotation>
	<folder></folder>
	<filename>video18_1275_JPEG.rf.c1a57bcb607c6ee84c74a82318264fd6.jpg</filename>
	<path>video18_1275_JPEG.rf.c1a57bcb607c6ee84c74a82318264fd6.jpg</path>
	<source>
		<database>roboflow.com</database>
	</source>
	<size>
		<width>640</width>
		<height>640</height>
		<depth>3</depth>
	</size>
	<segmented>0</segmented>
	<object>
		<name>drone</name>
		<pose>Unspecified</pose>
		<truncated>0</truncated>
		<difficult>0</difficult>
		<occluded>0</occluded>
		<bndbox>
			<xmin>483</xmin>
			<xmax>520</xmax>
			<ymin>199</ymin>
			<ymax>250</ymax>
		</bndbox>
	</object>
	<object>
		<name>drone</name>
		<pose>Unspecified</pose>
		<truncated>0</truncated>
		<difficult>0</difficult>
		<occluded>0</occluded>
		<bndbox>
			<xmin>205</xmin>
			<xmax>251</xmax>
			<ymin>99</ymin>
			<ymax>157</ymax>
		</bndbox>
	</object>
</annotation>
