<annotation>
	<folder></folder>
	<filename>WhatsApp-Image-2024-02-18-at-17-18-00-1-_jpeg.rf.4f302e3161ecec3b517d57b52f76cc22.jpg</filename>
	<path>WhatsApp-Image-2024-02-18-at-17-18-00-1-_jpeg.rf.4f302e3161ecec3b517d57b52f76cc22.jpg</path>
	<source>
		<database>roboflow.com</database>
	</source>
	<size>
		<width>640</width>
		<height>640</height>
		<depth>3</depth>
	</size>
	<segmented>0</segmented>
	<object>
		<name>drone</name>
		<pose>Unspecified</pose>
		<truncated>0</truncated>
		<difficult>0</difficult>
		<occluded>0</occluded>
		<bndbox>
			<xmin>115</xmin>
			<xmax>480</xmax>
			<ymin>66</ymin>
			<ymax>472</ymax>
		</bndbox>
	</object>
</annotation>
